byteark_sdk/__init__.py
byteark_sdk/signer.py
byteark_sdk-0.1.2.dist-info/METADATA
byteark_sdk-0.1.2.dist-info/WHEEL
byteark_sdk-0.1.2.dist-info/RECORD
