Metadata-Version: 2.3
Name: byteark-sdk
Version: 0.1.2
Summary: 
Author: Piyaboot Thavilthirakul
Author-email: piyaboot@inox.co.th
Requires-Python: >=3.9
Classifier: Programming Language :: Python :: 3
Classifier: Programming Language :: Python :: 3.9
Classifier: Programming Language :: Python :: 3.10
Classifier: Programming Language :: Python :: 3.11
Classifier: Programming Language :: Python :: 3.12
Classifier: Programming Language :: Python :: 3.13
